musy/__init__.py
musy/_modidx.py
musy/chord.py
musy/midi.py
musy/note.py
musy/scale.py
musy/viz.py
musy-0.0.13.dist-info/licenses/LICENSE
musy-0.0.13.dist-info/METADATA
musy-0.0.13.dist-info/WHEEL
musy-0.0.13.dist-info/entry_points.txt
musy-0.0.13.dist-info/top_level.txt
musy-0.0.13.dist-info/RECORD
