Metadata-Version: 2.4
Name: musy
Version: 0.0.13
Summary: Toolbox for analyzing, creating and visualizing music
Home-page: https://github.com/CarloLepelaars/musy
Author: Carlo Lepelaars
Author-email: info@carlolepelaars.nl
License: Apache Software License 2.0
Keywords: nbdev jupyter notebook python
Classifier: Development Status :: 4 - Beta
Classifier: Intended Audience :: Developers
Classifier: Natural Language :: English
Classifier: Programming Language :: Python :: 3.10
Classifier: Programming Language :: Python :: 3.11
Classifier: Programming Language :: Python :: 3.12
Classifier: Programming Language :: Python :: 3.13
Classifier: License :: OSI Approved :: Apache Software License
Requires-Python: >=3.10
License-File: LICENSE
Requires-Dist: fastcore
Requires-Dist: mingus
Requires-Dist: MIDIUtil
Requires-Dist: midi-player
Requires-Dist: numpy
Requires-Dist: scipy
Requires-Dist: python-fasthtml
Requires-Dist: pandas
Provides-Extra: dev
Dynamic: author
Dynamic: author-email
Dynamic: classifier
Dynamic: description
Dynamic: description-content-type
Dynamic: home-page
Dynamic: keywords
Dynamic: license
Dynamic: license-file
Dynamic: provides-extra
Dynamic: requires-dist
Dynamic: requires-python
Dynamic: summary
